flask_geomapper/__init__.py
flask_geomapper-3.0.1.dist-info/LICENSE
flask_geomapper-3.0.1.dist-info/METADATA
flask_geomapper-3.0.1.dist-info/WHEEL
flask_geomapper-3.0.1.dist-info/top_level.txt
flask_geomapper-3.0.1.dist-info/RECORD
