Metadata-Version: 2.1
Name: flask-geomapper
Version: 3.0.1
Summary: Visualize Flask request locations cartographically
Home-page: https://github.com/gadhagod/flask-geomapper
Author: Aarav Borthakur
Author-email: gadhaguy13@gmail.com
License: UNKNOWN
Platform: UNKNOWN
Classifier: Programming Language :: Python :: 3
Classifier: License :: OSI Approved :: MIT License
Classifier: Operating System :: OS Independent
Requires-Python: >=3.6
Requires-Dist: flask
Requires-Dist: pandas
Requires-Dist: geopandas
Requires-Dist: matplotlib
Requires-Dist: requests
